common_as/__init__.py
common_as/base_helper.py
common_as/calculate_ta.py
common_as/date_util.py
common_as/dbmysql.py
common_as/enums.py
common_as/file_util.py
common_as/helper_breeze.py
common_as/helper_ks.py
common_as/kitehelper.py
common_as/levels.py
common_as/log_util.py
common_as/telegram_util.py
common_as/util.py
common_as-1.3.2.dist-info/LICENSE.txt
common_as-1.3.2.dist-info/METADATA
common_as-1.3.2.dist-info/WHEEL
common_as-1.3.2.dist-info/top_level.txt
common_as-1.3.2.dist-info/RECORD
