Metadata-Version: 2.1
Name: common-as
Version: 1.3.2
Summary: common modules used in Arthasangraha suite of projects
Author: Arthasangraha
Author-email: roopesh@arthasangraha.com
License-File: LICENSE.txt
Requires-Dist: pandas
Requires-Dist: numpy
